README.md
setup.py
ssc_32u/__init__.py
ssc_32u/arm.py
ssc_32u/joystick_arm.py
ssc_32u/joystick_arm_evdev.py
ssc_32u.egg-info/PKG-INFO
ssc_32u.egg-info/SOURCES.txt
ssc_32u.egg-info/dependency_links.txt
ssc_32u.egg-info/requires.txt
ssc_32u.egg-info/top_level.txt