Metadata-Version: 1.0
Name: ssc-32u
Version: 0.2.2
Summary: simple interface to robot arms controlled with SSC-32U controller
Home-page: http://github.com/dwiel/ssc_32u
Author: Zach Dwiel
Author-email: zdwiel@gmail.com
License: Apache
Platform: UNKNOWN
